[
    {
      "title": "The History of Bacon: From Farm to Fork",
      "subtitle": "A sizzling journey through time",
      "slug": "history-of-bacon",
      "author": "Jacob Druery",
      "tags": ["bacon", "history", "food"],
      "date": "2025-04-20",
      "postState": "published",
      "html": "<p>Bacon has been a beloved food for centuries...</p>",
      "delta": {
        "ops": [{ "insert": "Bacon has been a beloved food for centuries...\n" }]
      }
    },
    {
      "title": "5 Unusual Bacon Recipes You Need to Try",
      "subtitle": "From bacon ice cream to bacon jam",
      "slug": "unusual-bacon-recipes",
      "author": "Jacob Druery",
      "tags": ["recipes", "bacon", "cooking"],
      "date": "2025-04-20",
      "postState": "published",
      "html": "<p>Think bacon is only for breakfast? Think again...</p>",
      "delta": {
        "ops": [{ "insert": "Think bacon is only for breakfast? Think again...\n" }]
      }
    },
    {
      "title": "Bacon vs. Pancetta: What's the Difference?",
      "subtitle": "A comparison of two crispy favourites",
      "slug": "bacon-vs-pancetta",
      "author": "Jacob Druery",
      "tags": ["bacon", "pancetta", "meat"],
      "date": "2025-04-20",
      "postState": "published",
      "html": "<p>Bacon and pancetta may look alike, but...</p>",
      "delta": {
        "ops": [{ "insert": "Bacon and pancetta may look alike, but...\n" }]
      }
    },
    {
      "title": "Is Bacon Really That Bad For You?",
      "subtitle": "A look at the nutritional facts",
      "slug": "is-bacon-bad",
      "author": "Jacob Druery",
      "tags": ["bacon", "health", "nutrition"],
      "date": "2025-04-20",
      "postState": "published",
      "html": "<p>There’s no denying bacon’s flavour, but...</p>",
      "delta": {
        "ops": [{ "insert": "There’s no denying bacon’s flavour, but...\n" }]
      }
    },
    {
      "title": "Making the Perfect Crispy Bacon Every Time",
      "subtitle": "Tips and tricks for that golden crunch",
      "slug": "perfect-crispy-bacon",
      "author": "Jacob Druery",
      "tags": ["bacon", "cooking tips"],
      "date": "2025-04-20",
      "postState": "published",
      "html": "<p>Ever wonder how to get that restaurant-style crisp?</p>",
      "delta": {
        "ops": [{ "insert": "Ever wonder how to get that restaurant-style crisp?\n" }]
      }
    },
    {
      "title": "The Bacon Lover’s Guide to Brunch",
      "subtitle": "Bringing bacon to the centre of the table",
      "slug": "bacon-brunch-guide",
      "author": "Jacob Druery",
      "tags": ["bacon", "brunch", "guide"],
      "date": "2025-04-20",
      "postState": "published",
      "html": "<p>Nothing says brunch like a plate full of bacon...</p>",
      "delta": {
        "ops": [{ "insert": "Nothing says brunch like a plate full of bacon...\n" }]
      }
    },
    {
      "title": "Why Bacon Makes Everything Better",
      "subtitle": "The science and psychology of umami",
      "slug": "bacon-makes-everything-better",
      "author": "Jacob Druery",
      "tags": ["bacon", "umami", "flavour"],
      "date": "2025-04-20",
      "postState": "published",
      "html": "<p>It’s more than just taste—it’s a feeling...</p>",
      "delta": {
        "ops": [{ "insert": "It’s more than just taste—it’s a feeling...\n" }]
      }
    },
    {
      "title": "Bacon Around the World",
      "subtitle": "How different cultures use bacon",
      "slug": "bacon-around-the-world",
      "author": "Jacob Druery",
      "tags": ["bacon", "world", "culture"],
      "date": "2025-04-20",
      "postState": "published",
      "html": "<p>From American streaky to Italian guanciale...</p>",
      "delta": {
        "ops": [{ "insert": "From American streaky to Italian guanciale...\n" }]
      }
    },
    {
      "title": "Vegetarian Bacon Alternatives: Are They Any Good?",
      "subtitle": "Exploring meat-free bacon options",
      "slug": "vegetarian-bacon-alternatives",
      "author": "Jacob Druery",
      "tags": ["bacon", "vegetarian", "alternatives"],
      "date": "2025-04-20",
      "postState": "published",
      "html": "<p>Even plant-based eaters want that smoky crunch...</p>",
      "delta": {
        "ops": [{ "insert": "Even plant-based eaters want that smoky crunch...\n" }]
      }
    },
    {
      "title": "Bacon Storage & Preservation Tips",
      "subtitle": "Keep your bacon fresh and tasty longer",
      "slug": "bacon-storage-tips",
      "author": "Jacob Druery",
      "tags": ["bacon", "kitchen", "preservation"],
      "date": "2025-04-20",
      "postState": "published",
      "html": "<p>Proper storage is key to keeping bacon delicious...</p>",
      "delta": {
        "ops": [{ "insert": "Proper storage is key to keeping bacon delicious...\n" }]
      }
    },
    {
      "title": "The Ultimate Guide to Home-Cured Bacon",
      "subtitle": "Make your own bacon from scratch",
      "slug": "home-cured-bacon-guide",
      "author": "Jacob Druery",
      "tags": ["bacon", "DIY", "home curing"],
      "date": "2025-04-20",
      "postState": "draft",
      "html": "<p>Turn pork belly into gourmet bacon at home...</p>",
      "delta": {
        "ops": [{ "insert": "Turn pork belly into gourmet bacon at home...\n" }]
      }
    },
    {
      "title": "Bacon Myths Busted",
      "subtitle": "Separating sizzling facts from fiction",
      "slug": "bacon-myths-busted",
      "author": "Jacob Druery",
      "tags": ["bacon", "myths", "facts"],
      "date": "2025-04-20",
      "postState": "draft",
      "html": "<p>Is bacon really banned in some places? Let’s dive in...</p>",
      "delta": {
        "ops": [{ "insert": "Is bacon really banned in some places? Let’s dive in...\n" }]
      }
    },
    {
      "title": "Pairing Bacon with Beverages",
      "subtitle": "Best drinks to complement bacon’s richness",
      "slug": "bacon-beverage-pairings",
      "author": "Jacob Druery",
      "tags": ["bacon", "pairing", "drinks"],
      "date": "2025-04-20",
      "postState": "draft",
      "html": "<p>From coffee to craft beer, bacon has a perfect match...</p>",
      "delta": {
        "ops": [{ "insert": "From coffee to craft beer, bacon has a perfect match...\n" }]
      }
    }
  ]
  